trython_validators.py
validators.py
trython_validators-0.1.0.dist-info/LICENSE
trython_validators-0.1.0.dist-info/METADATA
trython_validators-0.1.0.dist-info/WHEEL
trython_validators-0.1.0.dist-info/top_level.txt
trython_validators-0.1.0.dist-info/RECORD
